report_generator/__init__.py
report_generator/app.py
report_generator/config.py
report_generator/fonts.py
report_generator/excel_extraction/__init__.py
report_generator/excel_extraction/clean_data.py
report_generator/excel_extraction/data_structure.py
report_generator/excel_extraction/excel_to_sql.py
report_generator/excel_extraction/tables.py
report_generator/location_formatter/__init__.py
report_generator/location_formatter/clean_data.py
report_generator/location_formatter/location.py
report_generator/location_formatter/location_finder.py
report_generator/location_formatter/location_updater.py
report_generator/location_formatter/locations_setup.py
report_generator/location_formatter/main.py
report_generator/project_setup/__init__.py
report_generator/project_setup/locations_data_setup.py
report_generator/project_setup/locations_db_setup.py
report_generator/project_setup/locations_json_setup.py
report_generator/project_setup/new_report_project.py
report_generator/project_setup/project_directory_setup.py
report_generator/read_from_db/__init__.py
report_generator/read_from_db/query_db.py
report_generator/report_generator_cli/__init__.py
report_generator/report_generator_cli/amphibian.py
report_generator/report_generator_cli/create_report.py
report_generator/report_generator_cli/main.py
report_generator/report_generator_gui/__init__.py
report_generator/report_generator_gui/app.py
report_generator/report_generator_gui/main.py
report_generator/report_generator_gui/ui/__init__.py
report_generator/report_generator_gui/ui/report_gui.py
report_generator/report_generator_gui/ui/report_setup.py
report_generator/report_generator_gui/ui/window_ui.py
qub_amphibian_report_generator-0.0.34.dist-info/LICENSE
qub_amphibian_report_generator-0.0.34.dist-info/METADATA
qub_amphibian_report_generator-0.0.34.dist-info/WHEEL
qub_amphibian_report_generator-0.0.34.dist-info/entry_points.txt
qub_amphibian_report_generator-0.0.34.dist-info/top_level.txt
qub_amphibian_report_generator-0.0.34.dist-info/RECORD
