Metadata-Version: 2.1
Name: qub-amphibian-report-generator
Version: 0.0.34
Summary: Generate reports from amphibian info dataset
Author: Ciaran Cushnahan
License: LICENSE
License-File: LICENSE
Requires-Dist: docopt (<=0.6.2)
Requires-Dist: PyQt5 (<=5.15.7)
Requires-Dist: pandas (<=1.4.4)
Requires-Dist: openpyxl (<=3.0.10)
Requires-Dist: loguru (<=0.6.0)
Requires-Dist: PyPDF2 (<=2.10.4)
Requires-Dist: fpdf2 (<=2.5.5)
Requires-Dist: PyMuPDF (<=1.20.2)
Requires-Dist: PyYAML (<=6.0)
Requires-Dist: requests (<=2.28.1)
Requires-Dist: tqdm (<=4.64.1)
